scribble_annotation_generator/__init__.py
scribble_annotation_generator/cli.py
scribble_annotation_generator/crop_field.py
scribble_annotation_generator/dataset.py
scribble_annotation_generator/debug.py
scribble_annotation_generator/nn.py
scribble_annotation_generator/utils.py
scribble_annotation_generator-0.0.1.dist-info/METADATA
scribble_annotation_generator-0.0.1.dist-info/WHEEL
scribble_annotation_generator-0.0.1.dist-info/entry_points.txt
scribble_annotation_generator-0.0.1.dist-info/RECORD
