Metadata-Version: 2.4
Name: scribble-annotation-generator
Version: 0.0.1
Summary: Programmatically generate semi-realistic synthetic scribble annotations based on statistics from existing scribble datasets
Project-URL: Homepage, https://github.com/alexsenden/scribble-annotation-generator
Project-URL: Repository, https://github.com/alexsenden/scribble-annotation-generator
Project-URL: Issues, https://github.com/alexsenden/scribble-annotation-generator/issues
Author: Alex Senden
License: MIT
Keywords: annotation,computer-vision,scribble,segmentation,synthetic-data
Classifier: Development Status :: 3 - Alpha
Classifier: Intended Audience :: Developers
Classifier: Intended Audience :: Science/Research
Classifier: License :: OSI Approved :: MIT License
Classifier: Programming Language :: Python :: 3
Classifier: Programming Language :: Python :: 3.8
Classifier: Programming Language :: Python :: 3.9
Classifier: Programming Language :: Python :: 3.10
Classifier: Programming Language :: Python :: 3.11
Classifier: Programming Language :: Python :: 3.12
Classifier: Topic :: Scientific/Engineering :: Artificial Intelligence
Classifier: Topic :: Scientific/Engineering :: Image Processing
Requires-Python: >=3.8
Requires-Dist: numpy
Requires-Dist: opencv-python
Requires-Dist: scikit-image
Requires-Dist: scipy
